[
    {
        "type": "message",
        "user": "U18VAQPB9",
        "text": "<https:\/\/www.youtube.com\/watch?v=Mb7ei3id2Eo>",
        "attachments": [
            {
                "service_name": "YouTube",
                "service_url": "https:\/\/www.youtube.com\/",
                "title": "Bangs Meet Me On Facebook.",
                "title_link": "https:\/\/www.youtube.com\/watch?v=Mb7ei3id2Eo",
                "author_name": "Kwaku Carter",
                "author_link": "https:\/\/www.youtube.com\/user\/yungcarter1515",
                "thumb_url": "https:\/\/i.ytimg.com\/vi\/Mb7ei3id2Eo\/hqdefault.jpg",
                "thumb_width": 480,
                "thumb_height": 360,
                "fallback": "YouTube Video: Bangs Meet Me On Facebook.",
                "video_html": "<iframe width=\"400\" height=\"225\" src=\"https:\/\/www.youtube.com\/embed\/Mb7ei3id2Eo?feature=oembed&autoplay=1&iv_load_policy=3\" frameborder=\"0\" gesture=\"media\" allowfullscreen><\/iframe>",
                "video_html_width": 400,
                "video_html_height": 225,
                "from_url": "https:\/\/www.youtube.com\/watch?v=Mb7ei3id2Eo",
                "service_icon": "https:\/\/a.slack-edge.com\/2089\/img\/unfurl_icons\/youtube.png",
                "id": 1
            }
        ],
        "ts": "1510256520.000631"
    },
    {
        "type": "message",
        "user": "U18VAQPB9",
        "text": "<https:\/\/www.youtube.com\/watch?v=byNlqUFddeo>",
        "attachments": [
            {
                "service_name": "YouTube",
                "service_url": "https:\/\/www.youtube.com\/",
                "title": "Take you to the movies - Bangs \" With Lyrics \"",
                "title_link": "https:\/\/www.youtube.com\/watch?v=byNlqUFddeo",
                "author_name": "FueledbyStriker",
                "author_link": "https:\/\/www.youtube.com\/user\/FueledbyStriker",
                "thumb_url": "https:\/\/i.ytimg.com\/vi\/byNlqUFddeo\/hqdefault.jpg",
                "thumb_width": 480,
                "thumb_height": 360,
                "fallback": "YouTube Video: Take you to the movies - Bangs \" With Lyrics \"",
                "video_html": "<iframe width=\"400\" height=\"300\" src=\"https:\/\/www.youtube.com\/embed\/byNlqUFddeo?feature=oembed&autoplay=1&iv_load_policy=3\" frameborder=\"0\" gesture=\"media\" allowfullscreen><\/iframe>",
                "video_html_width": 400,
                "video_html_height": 300,
                "from_url": "https:\/\/www.youtube.com\/watch?v=byNlqUFddeo",
                "service_icon": "https:\/\/a.slack-edge.com\/2089\/img\/unfurl_icons\/youtube.png",
                "id": 1
            }
        ],
        "ts": "1510256545.000130"
    },
    {
        "type": "message",
        "user": "U1908M6PL",
        "text": "take you to the movies is a gem",
        "ts": "1510256564.000187"
    },
    {
        "type": "message",
        "user": "U18VAQPB9",
        "text": "yo boi k$adilla back <https:\/\/soundcloud.com\/thunderstone-radio\/fnk4>",
        "attachments": [
            {
                "service_name": "SoundCloud",
                "service_url": "http:\/\/soundcloud.com",
                "title": "THE FUNKSHUN VOL. 4 | MIXED BY K-$ADILLA &amp; CURATED BY BLR &amp; K-$ADILLA (11\/09\/17 | FUTURE FUNK MUSIC) by THUNDERSTONE RADIO",
                "title_link": "https:\/\/soundcloud.com\/thunderstone-radio\/fnk4",
                "author_name": "THUNDERSTONE RADIO",
                "author_link": "https:\/\/soundcloud.com\/thunderstone-radio",
                "thumb_url": "http:\/\/i1.sndcdn.com\/artworks-000253636184-wbyfjv-t500x500.jpg",
                "text": "Tracklist:\n\n1. Let Me Be The One - Harrison\n2. Do a Breakdown - Bewilderbeast\n3. So Fine - Nova Black\n4. She Paused - Patrick Gibin aka Twice\n5. Electrify - Shiro Schwarz\n6. Last Night Was Fun - Dr GoFast\n7. Love Is What You Need - 3 Monkeyzz\n8. In Motion - COEO\n9. WHYNOT - Channel Tres\n10. Take My Love Away - Ziggy Phunk\n11. Make It Hot - Stephane Deschezeaux\n12. Can't Take My Eyes Off You - Lola Disco\n13. Poppin Off - SKY\n14. Mental Geller - The Phantom's Revenge\n15. Everything I Touch - Cyan Blue\n16. Space House - Consumer.Electronics\n17. Hold You - k a z z e t t e\n18. The Thrill - Nico Flicker\n19. What Would I Do - REMLARЯ\n20. Eu Queria Ter O Cabelo Do Sunson - Maffalda",
                "fallback": "SoundCloud Audio: THE FUNKSHUN VOL. 4 | MIXED BY K-$ADILLA & CURATED BY BLR & K-$ADILLA (11\/09\/17 | FUTURE FUNK MUSIC) by THUNDERSTONE RADIO",
                "audio_html": "<iframe width=\"100%\" height=\"150\" scrolling=\"no\" frameborder=\"no\" src=\"https:\/\/w.soundcloud.com\/player\/?visual=true&url=https%3A%2F%2Fapi.soundcloud.com%2Ftracks%2F353509067&show_artwork=true&maxheight=150\"><\/iframe>",
                "audio_html_width": 100,
                "audio_html_height": 150,
                "from_url": "https:\/\/soundcloud.com\/thunderstone-radio\/fnk4",
                "thumb_width": 500,
                "thumb_height": 500,
                "service_icon": "https:\/\/soundcloud.com\/favicon.ico",
                "id": 1
            }
        ],
        "ts": "1510277629.000035"
    },
    {
        "type": "message",
        "user": "U18VAQPB9",
        "text": "<https:\/\/soundcloud.com\/fibremusic\/wip>",
        "attachments": [
            {
                "service_name": "SoundCloud",
                "service_url": "http:\/\/soundcloud.com",
                "title": "wip by FIBRE",
                "title_link": "https:\/\/soundcloud.com\/fibremusic\/wip",
                "author_name": "FIBRE",
                "author_link": "https:\/\/soundcloud.com\/fibremusic",
                "thumb_url": "http:\/\/i1.sndcdn.com\/artworks-000253495631-pvr22w-t500x500.jpg",
                "text": "intro track demo from my second ep, out 2018",
                "fallback": "SoundCloud Audio: wip by FIBRE",
                "audio_html": "<iframe width=\"100%\" height=\"150\" scrolling=\"no\" frameborder=\"no\" src=\"https:\/\/w.soundcloud.com\/player\/?visual=true&url=https%3A%2F%2Fapi.soundcloud.com%2Ftracks%2F353367644&show_artwork=true&maxheight=150\"><\/iframe>",
                "audio_html_width": 100,
                "audio_html_height": 150,
                "from_url": "https:\/\/soundcloud.com\/fibremusic\/wip",
                "thumb_width": 500,
                "thumb_height": 500,
                "service_icon": "https:\/\/soundcloud.com\/favicon.ico",
                "id": 1
            }
        ],
        "ts": "1510281822.000135"
    }
]